{
  "_format": "hh-sol-cache-2",
  "files": {
    "/Users/harrychan/development/protocols/contracts/Token.sol": {
      "lastModificationDate": 1611295238653,
      "contentHash": "a0962d8c36a95b9a363b3f76f37c51fb",
      "sourceName": "contracts/Token.sol",
      "solcConfig": {
        "version": "0.6.11",
        "settings": {
          "optimizer": {
            "enabled": false,
            "runs": 200
          },
          "outputSelection": {
            "*": {
              "*": [
                "abi",
                "evm.bytecode",
                "evm.deployedBytecode",
                "evm.methodIdentifiers"
              ],
              "": [
                "ast"
              ]
            }
          }
        }
      },
      "imports": [],
      "versionPragmas": [
        "^0.6.11"
      ],
      "artifacts": [
        "Token"
      ]
    }
  }
}
